pmw3901/__init__.py
pmw3901-0.1.0.dist-info/LICENSE.txt
pmw3901-0.1.0.dist-info/METADATA
pmw3901-0.1.0.dist-info/WHEEL
pmw3901-0.1.0.dist-info/top_level.txt
pmw3901-0.1.0.dist-info/RECORD
